stix_traverser/__init__.py
stix_traverser-0.1.1.dist-info/licenses/LICENSE
stix_traverser-0.1.1.dist-info/METADATA
stix_traverser-0.1.1.dist-info/WHEEL
stix_traverser-0.1.1.dist-info/top_level.txt
stix_traverser-0.1.1.dist-info/RECORD
