Metadata-Version: 2.4
Name: stix-traverser
Version: 0.1.1
Summary: STIX cyber threat intelligence graph traverser.
Author-email: Alexander Gor <alex@alexandergor.com>
License: BSD-3-Clause
Project-URL: Homepage, https://github.com/orn0t/stix-traverser
Requires-Python: >=3.9
License-File: LICENSE
Dynamic: license-file
